<?xml version="1.0" encoding="utf-8"?>
<ObjDef xmlns="http://www.sonicretro.org">
  <Images>
    <ImageFromSheet id="projector" sheet="Global/Items3.gif" sourcex="150" sourcey="86" width="24" height="24">
      <Offset X="-12" Y="-12" />
    </ImageFromSheet>
    <ImageFromSheet id="light" sheet="Global/Items3.gif" sourcex="158" sourcey="111" width="16" height="8">
      <Offset X="-29" Y="-10" />
    </ImageFromSheet>
    <ImageFromSheet id="metal" sheet="Global/Items3.gif" sourcex="175" sourcey="136" width="40" height="40">
      <Offset X="-108" Y="-28" />
    </ImageFromSheet>
    <ImageFromSheet id="squirrel" sheet="Global/Items3.gif" sourcex="150" sourcey="52" width="24" height="16">
      <Offset X="-112" Y="-3" />
    </ImageFromSheet>
    <ImageFromSheet id="bluebird" sheet="Global/Items3.gif" sourcex="240" sourcey="199" width="16" height="16">
      <Offset X="-96" Y="-32" />
    </ImageFromSheet>
  </Images>
  <ImageSets>
    <ImageSet id="img">
      <ImageRef image="projector" />
      <ImageRef image="light" />
      <ImageRef image="metal" />
      <ImageRef image="squirrel" />
      <ImageRef image="bluebird" />
    </ImageSet>
  </ImageSets>
  <DefaultImage>
    <ImageSetRef set="img" />
  </DefaultImage>
</ObjDef>